AUTHORS
CHANGES
LICENSE
MANIFEST.in
README
README.rst
setup.py
django_reploc.egg-info/PKG-INFO
django_reploc.egg-info/SOURCES.txt
django_reploc.egg-info/dependency_links.txt
django_reploc.egg-info/not-zip-safe
django_reploc.egg-info/top_level.txt
reploc/__init__.py
reploc/admin.py
reploc/context_processors.py
reploc/models.py
reploc/urls.py
reploc/utils.py
reploc/views.py
reploc/management/__init__.py
reploc/management/commands/__init__.py
reploc/management/commands/reploc_update_coords.py
reploc/media/img/ajax.gif
reploc/media/js/jquery-1.3.1.min.js
reploc/templates/base.html
reploc/templates/reploc/json.js
reploc/templates/reploc/locator.html
reploc/templates/reploc/locator.js
sample/__init__.py
sample/manage.py
sample/settings.py
sample/urls.py