Metadata-Version: 1.0
Name: django-reploc
Version: 0.1.1-pre1
Summary: A simple way for people to find representative locations on your Django-powered Web site.
Home-page: http://bitbucket.org/codekoala/django-reploc/
Author: Josh VanderLinden
Author-email: codekoala at gmail dot com
License: MIT
Keywords: django,dealers,vendors,representatives,locator,map
Platform: UNKNOWN
Classifier: Development Status :: 4 - Beta
Classifier: Environment :: Web Environment
Classifier: Framework :: Django
Classifier: Intended Audience :: Developers
Classifier: Intended Audience :: End Users/Desktop
Classifier: License :: OSI Approved :: MIT License
Classifier: Operating System :: OS Independent
Classifier: Programming Language :: Python
Classifier: Topic :: Communications
Classifier: Topic :: Internet :: WWW/HTTP :: Dynamic Content
